clownload.py
clownload-0.0.4.dist-info/METADATA
clownload-0.0.4.dist-info/WHEEL
clownload-0.0.4.dist-info/entry_points.txt
clownload-0.0.4.dist-info/RECORD
