Metadata-Version: 2.4
Name: clownload
Version: 0.0.4
Summary: download files from clown computers
Author: Lawrence D'Anna
Author-email: larry@elder-gods.org
Requires-Python: >=3.10
Classifier: Programming Language :: Python :: 3
Classifier: Programming Language :: Python :: 3.10
Classifier: Programming Language :: Python :: 3.11
Classifier: Programming Language :: Python :: 3.12
Classifier: Programming Language :: Python :: 3.13
Classifier: Programming Language :: Python :: 3.14
Requires-Dist: dropbox
Requires-Dist: tenacity
Project-URL: Homepage, https://github.com/smoofra/clownload
